README.md
package_info.json
setup.py
th2_grpc_check2_recon/__init__.py
th2_grpc_check2_recon/check2_recon.proto
th2_grpc_check2_recon/check2_recon_pb2.py
th2_grpc_check2_recon/check2_recon_pb2.pyi
th2_grpc_check2_recon/check2_recon_pb2_grpc.py
th2_grpc_check2_recon/check2_recon_service.py
th2_grpc_check2_recon/py.typed
th2_grpc_check2_recon.egg-info/PKG-INFO
th2_grpc_check2_recon.egg-info/SOURCES.txt
th2_grpc_check2_recon.egg-info/dependency_links.txt
th2_grpc_check2_recon.egg-info/requires.txt
th2_grpc_check2_recon.egg-info/top_level.txt