Metadata-Version: 2.1
Name: th2-grpc-check2-recon
Version: 1.0.3
Summary: th2_grpc_check2_recon
Home-page: https://github.com/th2-net/th2-grpc-check2-recon
Author: TH2-devs
Author-email: th2-devs@exactprosystems.com
License: Apache License 2.0
Platform: UNKNOWN
Requires-Python: >=3.7
